mscolorlog/__init__.py
mscolorlog/core.py
mscolorlog-1.0.1.dist-info/METADATA
mscolorlog-1.0.1.dist-info/WHEEL
mscolorlog-1.0.1.dist-info/licenses/LICENSE
mscolorlog-1.0.1.dist-info/RECORD
