Metadata-Version: 2.1
Name: mscolorlog
Version: 1.0.1
Summary: A lightweight and highly customizable package that can ouput colored logs to the console.
Project-URL: Homepage, https://github.com/MiSAKASiRiN/mscolorlog
Project-URL: Bug Tracker, https://github.com/MiSAKASiRiN/mscolorlog/issues
Author-email: sirin <misaka@sirin.moe>
License-File: LICENSE
Classifier: License :: OSI Approved :: MIT License
Classifier: Operating System :: OS Independent
Classifier: Programming Language :: Python :: 3
Requires-Python: >=3.6
Requires-Dist: psutil
